[
  {
    "number": 16818,
    "name": "Hype-Birds"
  },
  {
    "number": 25845,
    "name": "Girlbotics"
  },
  {
    "number": 11111,
    "name": "MercaMex"
  },
  {
    "number": 99999,
    "name": "Hidalgo"
  },
  {
    "number": 21735,
    "name": "Nautilus Black"
  },
  {
    "number": 28255,
    "name": "Techkalli"
  },
  {
    "number": 28254,
    "name": "Waachma"
  },
  {
    "number": 21802,
    "name": "VOLTEC NOVA"
  },
  {
    "number": 23481,
    "name": "VOLTEC SURGE"
  },
  {
    "number": 26333,
    "name": "Low Altitude Robotics"
  },
  {
    "number": 23651,
    "name": "Dynastia"
  },
  {
    "number": 23897,
    "name": "Valkyries"
  },
  {
    "number": 23898,
    "name": "Amazonas"
  }
]